symb_anafis/__init__.py
symb_anafis/__init__.pyi
symb_anafis/py.typed
symb_anafis/symb_anafis.cpython-314-darwin.so
symb_anafis-0.7.0.dist-info/METADATA
symb_anafis-0.7.0.dist-info/WHEEL
symb_anafis-0.7.0.dist-info/licenses/LICENSE
symb_anafis-0.7.0.dist-info/RECORD
