Metadata-Version: 2.4
Name: symb_anafis
Version: 0.7.0
Classifier: Development Status :: 4 - Beta
Classifier: Intended Audience :: Developers
Classifier: Intended Audience :: Science/Research
Classifier: License :: OSI Approved :: Apache Software License
Classifier: Programming Language :: Python :: 3
Classifier: Programming Language :: Python :: 3.9
Classifier: Programming Language :: Python :: 3.10
Classifier: Programming Language :: Python :: 3.11
Classifier: Programming Language :: Python :: 3.12
Classifier: Programming Language :: Python :: 3.13
Classifier: Programming Language :: Python :: 3.14
Classifier: Programming Language :: Rust
Classifier: Topic :: Scientific/Engineering :: Mathematics
License-File: LICENSE
Summary: Fast symbolic differentiation library - Rust-powered Python bindings
Keywords: symbolic,differentiation,calculus,mathematics,derivatives,fast
Author: CokieMiner
License: Apache-2.0
Requires-Python: >=3.9
Project-URL: Documentation, https://docs.rs/symb_anafis
Project-URL: Homepage, https://github.com/CokieMiner/SymbAnaFis
Project-URL: Repository, https://github.com/CokieMiner/SymbAnaFis
